riptide/__init__.py
riptide/cloud/__init__.py
riptide/cloud/alarms.py
riptide/cloud/app.py
riptide/cloud/client.py
riptide/cloud/entity.py
riptide/cloud/exception.py
riptide/cloud/history.py
riptide/cloud/watch.py
riptide_cloud-0.0.2.dist-info/METADATA
riptide_cloud-0.0.2.dist-info/WHEEL
riptide_cloud-0.0.2.dist-info/namespace_packages.txt
riptide_cloud-0.0.2.dist-info/top_level.txt
riptide_cloud-0.0.2.dist-info/zip-safe
riptide_cloud-0.0.2.dist-info/RECORD
