Metadata-Version: 2.1
Name: riptide-cloud
Version: 0.0.2
Summary: Riptide Cloud API.
Home-page: UNKNOWN
Author: Sangeeth Saravanaraj
Author-email: sangeeth@riptideio.com
Maintainer: Sangeeth Saravanaraj
Maintainer-email: sangeeth@riptideio.com
License: MIT
Keywords: riptide alarm entity watch history IoT cloud
Platform: UNKNOWN
Classifier: Programming Language :: Python
Classifier: Programming Language :: Python :: 3
Classifier: Programming Language :: Python :: 3.6
Classifier: Operating System :: OS Independent
Classifier: Development Status :: 5 - Production/Stable
Classifier: Environment :: Console
Classifier: Intended Audience :: Developers
Classifier: License :: OSI Approved :: MIT License
Classifier: Topic :: Software Development :: Libraries
Requires-Python: >=3.6
Requires-Dist: requests (==2.24.0)
